displaypad/DisplayPad.py
displaypad/__init__.py
DisplayPad-1.0.3.dist-info/LICENSE
DisplayPad-1.0.3.dist-info/METADATA
DisplayPad-1.0.3.dist-info/WHEEL
DisplayPad-1.0.3.dist-info/top_level.txt
DisplayPad-1.0.3.dist-info/RECORD
