Metadata-Version: 2.1
Name: DisplayPad
Version: 1.0.3
Summary: This library allows you to customize your own Mountain DisplayPad by assigning each button its own custom function, image or color.
Home-page: https://sytxlabs.eu
Author: Sytxlabs
Author-email: Sytxlabs <info@sytxlabs.eu>
License: MIT license
Project-URL: Homepage, https://sytxlabs.eu
Project-URL: GitHub, https://github.com/SytxLabs/DisplayPad
Requires-Python: >=3.10
License-File: LICENSE
Requires-Dist: hidapi==0.14.0.post2
Requires-Dist: pyee==12.0.0
Requires-Dist: Pillow==11.0.0
